gitmon/__init__.py
gitmon/__main__.py
gitmon/tool.py
pygitmon-0.0.2.dist-info/LICENSE
pygitmon-0.0.2.dist-info/METADATA
pygitmon-0.0.2.dist-info/WHEEL
pygitmon-0.0.2.dist-info/top_level.txt
pygitmon-0.0.2.dist-info/RECORD
