Metadata-Version: 2.1
Name: pygitmon
Version: 0.0.2
Summary: Update git working directory and run commands
Author-email: Fahri Reza <dozymoe@gmail.com>
License: GNU GENERAL PUBLIC LICENSE
Project-URL: Homepage, https://github.com/dozymoe/pygitmon
Project-URL: Issues, https://github.com/dozymoe/pygitmon/issues
Classifier: Programming Language :: Python :: 3
Classifier: License :: OSI Approved :: MIT License
Classifier: Operating System :: OS Independent
Requires-Python: >=3.8
License-File: LICENSE
Requires-Dist: pygit2
